hhutil/__init__.py
hhutil/_version.py
hhutil/datetime.py
hhutil/functools.py
hhutil/hash.py
hhutil/io.py
hhutil-0.2.4.dist-info/METADATA
hhutil-0.2.4.dist-info/WHEEL
hhutil-0.2.4.dist-info/top_level.txt
hhutil-0.2.4.dist-info/RECORD
