Metadata-Version: 2.1
Name: hhutil
Version: 0.2.4
Summary: HrvvI's utility
Home-page: https://github.com/sbl1996/hhutil
Author: HrvvI
Author-email: sbl1996@126.com
License: MIT
Platform: UNKNOWN
Requires-Python: >=3.6.0
Requires-Dist: toolz
Requires-Dist: requests
Requires-Dist: python-dateutil
Requires-Dist: pytz
